[
  {
    "date": "2025-01-01",
    "open": 52740.0,
    "high": 53164.34,
    "low": 51966.66,
    "close": 52273.08,
    "volume": 264848
  },
  {
    "date": "2025-01-02",
    "open": 52273.08,
    "high": 52713.17,
    "low": 51812.0,
    "close": 52125.57,
    "volume": 247854
  },
  {
    "date": "2025-01-03",
    "open": 52125.57,
    "high": 52323.61,
    "low": 51560.44,
    "close": 51884.52,
    "volume": 333375
  },
  {
    "date": "2025-01-04",
    "open": 51884.52,
    "high": 51908.28,
    "low": 51239.31,
    "close": 51412.13,
    "volume": 223570
  },
  {
    "date": "2025-01-05",
    "open": 51412.13,
    "high": 52278.06,
    "low": 51158.59,
    "close": 52001.16,
    "volume": 212937
  },
  {
    "date": "2025-01-06",
    "open": 52001.16,
    "high": 53018.69,
    "low": 51961.5,
    "close": 53009.98,
    "volume": 248153
  },
  {
    "date": "2025-01-07",
    "open": 53009.98,
    "high": 54032.51,
    "low": 52550.63,
    "close": 53907.81,
    "volume": 153728
  },
  {
    "date": "2025-01-08",
    "open": 53907.81,
    "high": 54196.21,
    "low": 53498.05,
    "close": 53896.13,
    "volume": 126899
  },
  {
    "date": "2025-01-09",
    "open": 53896.13,
    "high": 54875.92,
    "low": 53658.3,
    "close": 54345.54,
    "volume": 135578
  },
  {
    "date": "2025-01-10",
    "open": 54345.54,
    "high": 54462.13,
    "low": 53598.72,
    "close": 53798.24,
    "volume": 109598
  },
  {
    "date": "2025-01-11",
    "open": 53798.24,
    "high": 54292.22,
    "low": 53115.13,
    "close": 53333.33,
    "volume": 173508
  },
  {
    "date": "2025-01-12",
    "open": 53333.33,
    "high": 54174.91,
    "low": 52857.01,
    "close": 53697.11,
    "volume": 124505
  },
  {
    "date": "2025-01-13",
    "open": 53697.11,
    "high": 53824.21,
    "low": 53350.82,
    "close": 53414.26,
    "volume": 311134
  },
  {
    "date": "2025-01-14",
    "open": 53414.26,
    "high": 53733.85,
    "low": 52544.4,
    "close": 52939.55,
    "volume": 345962
  },
  {
    "date": "2025-01-15",
    "open": 52939.55,
    "high": 53573.94,
    "low": 52574.8,
    "close": 53550.29,
    "volume": 241839
  },
  {
    "date": "2025-01-16",
    "open": 53550.29,
    "high": 53955.84,
    "low": 52510.55,
    "close": 52895.98,
    "volume": 342805
  },
  {
    "date": "2025-01-17",
    "open": 52895.98,
    "high": 54116.47,
    "low": 52781.54,
    "close": 53677.88,
    "volume": 207953
  },
  {
    "date": "2025-01-18",
    "open": 53677.88,
    "high": 54623.49,
    "low": 53407.51,
    "close": 54568.87,
    "volume": 160117
  },
  {
    "date": "2025-01-19",
    "open": 54568.87,
    "high": 55710.42,
    "low": 54335.8,
    "close": 55556.15,
    "volume": 191477
  },
  {
    "date": "2025-01-20",
    "open": 55556.15,
    "high": 57009.43,
    "low": 55247.1,
    "close": 56583.17,
    "volume": 143068
  },
  {
    "date": "2025-02-01",
    "open": 56583.17,
    "high": 56638.35,
    "low": 55226.07,
    "close": 55574.63,
    "volume": 105599
  },
  {
    "date": "2025-02-02",
    "open": 55574.63,
    "high": 56115.51,
    "low": 55117.64,
    "close": 56007.67,
    "volume": 161399
  },
  {
    "date": "2025-02-03",
    "open": 56007.67,
    "high": 57015.87,
    "low": 55897.97,
    "close": 56601.29,
    "volume": 154806
  },
  {
    "date": "2025-02-04",
    "open": 56601.29,
    "high": 56768.27,
    "low": 55944.71,
    "close": 55979.01,
    "volume": 217825
  },
  {
    "date": "2025-02-05",
    "open": 55979.01,
    "high": 56054.31,
    "low": 55360.88,
    "close": 55426.22,
    "volume": 339138
  },
  {
    "date": "2025-02-06",
    "open": 55426.22,
    "high": 56189.2,
    "low": 55006.87,
    "close": 55983.94,
    "volume": 299515
  },
  {
    "date": "2025-02-07",
    "open": 55983.94,
    "high": 56368.42,
    "low": 55511.16,
    "close": 55596.74,
    "volume": 116585
  },
  {
    "date": "2025-02-08",
    "open": 55596.74,
    "high": 56489.54,
    "low": 55386.54,
    "close": 56399.82,
    "volume": 144924
  },
  {
    "date": "2025-02-09",
    "open": 56399.82,
    "high": 56700.45,
    "low": 55794.31,
    "close": 56178.82,
    "volume": 334068
  },
  {
    "date": "2025-02-10",
    "open": 56178.82,
    "high": 56226.47,
    "low": 55973.33,
    "close": 56061.64,
    "volume": 119192
  },
  {
    "date": "2025-02-11",
    "open": 56061.64,
    "high": 56122.44,
    "low": 55219.95,
    "close": 55346.83,
    "volume": 313018
  },
  {
    "date": "2025-02-12",
    "open": 55346.83,
    "high": 55741.84,
    "low": 54278.52,
    "close": 54668.7,
    "volume": 331690
  },
  {
    "date": "2025-02-13",
    "open": 54668.7,
    "high": 55639.79,
    "low": 54159.16,
    "close": 55116.2,
    "volume": 335660
  },
  {
    "date": "2025-02-14",
    "open": 55116.2,
    "high": 56524.23,
    "low": 54934.29,
    "close": 56195.14,
    "volume": 218765
  },
  {
    "date": "2025-02-15",
    "open": 56195.14,
    "high": 56755.52,
    "low": 55191.19,
    "close": 55486.85,
    "volume": 248712
  },
  {
    "date": "2025-02-16",
    "open": 55486.85,
    "high": 55736.01,
    "low": 54822.1,
    "close": 54916.64,
    "volume": 319333
  },
  {
    "date": "2025-02-17",
    "open": 54916.64,
    "high": 55779.73,
    "low": 54773.73,
    "close": 55624.44,
    "volume": 156137
  },
  {
    "date": "2025-02-18",
    "open": 55624.44,
    "high": 57086.05,
    "low": 55159.63,
    "close": 56633.94,
    "volume": 151450
  },
  {
    "date": "2025-02-19",
    "open": 56633.94,
    "high": 56846.61,
    "low": 56180.44,
    "close": 56482.88,
    "volume": 343072
  },
  {
    "date": "2025-02-20",
    "open": 56482.88,
    "high": 56811.27,
    "low": 55177.93,
    "close": 55621.0,
    "volume": 133234
  },
  {
    "date": "2025-03-01",
    "open": 55621.0,
    "high": 56703.94,
    "low": 55231.51,
    "close": 56573.97,
    "volume": 348922
  },
  {
    "date": "2025-03-02",
    "open": 56573.97,
    "high": 57766.2,
    "low": 56350.73,
    "close": 57444.48,
    "volume": 270303
  },
  {
    "date": "2025-03-03",
    "open": 57444.48,
    "high": 58118.56,
    "low": 57366.8,
    "close": 57693.01,
    "volume": 235778
  },
  {
    "date": "2025-03-04",
    "open": 57693.01,
    "high": 58198.28,
    "low": 56561.99,
    "close": 57017.52,
    "volume": 163041
  },
  {
    "date": "2025-03-05",
    "open": 57017.52,
    "high": 58305.71,
    "low": 56671.48,
    "close": 58010.77,
    "volume": 331845
  },
  {
    "date": "2025-03-06",
    "open": 58010.77,
    "high": 58323.45,
    "low": 57038.77,
    "close": 57086.48,
    "volume": 237645
  },
  {
    "date": "2025-03-07",
    "open": 57086.48,
    "high": 57383.67,
    "low": 56896.91,
    "close": 57235.06,
    "volume": 135698
  },
  {
    "date": "2025-03-08",
    "open": 57235.06,
    "high": 58074.74,
    "low": 56954.31,
    "close": 58049.19,
    "volume": 319650
  },
  {
    "date": "2025-03-09",
    "open": 58049.19,
    "high": 58515.25,
    "low": 57302.13,
    "close": 57428.76,
    "volume": 266788
  },
  {
    "date": "2025-03-10",
    "open": 57428.76,
    "high": 57513.66,
    "low": 56298.54,
    "close": 56548.69,
    "volume": 210656
  },
  {
    "date": "2025-03-11",
    "open": 56548.69,
    "high": 57422.84,
    "low": 56131.5,
    "close": 57110.6,
    "volume": 184369
  },
  {
    "date": "2025-03-12",
    "open": 57110.6,
    "high": 57499.72,
    "low": 56517.39,
    "close": 57084.1,
    "volume": 188521
  },
  {
    "date": "2025-03-13",
    "open": 57084.1,
    "high": 57521.06,
    "low": 55636.22,
    "close": 56073.62,
    "volume": 303241
  },
  {
    "date": "2025-03-14",
    "open": 56073.62,
    "high": 56518.8,
    "low": 55619.65,
    "close": 56505.12,
    "volume": 107955
  },
  {
    "date": "2025-03-15",
    "open": 56505.12,
    "high": 56598.31,
    "low": 55213.35,
    "close": 55626.2,
    "volume": 266996
  },
  {
    "date": "2025-03-16",
    "open": 55626.2,
    "high": 55924.57,
    "low": 55520.28,
    "close": 55878.39,
    "volume": 349846
  },
  {
    "date": "2025-03-17",
    "open": 55878.39,
    "high": 56870.97,
    "low": 55378.67,
    "close": 56622.41,
    "volume": 269750
  },
  {
    "date": "2025-03-18",
    "open": 56622.41,
    "high": 57068.29,
    "low": 55971.65,
    "close": 56393.74,
    "volume": 258563
  },
  {
    "date": "2025-03-19",
    "open": 56393.74,
    "high": 56478.21,
    "low": 55190.49,
    "close": 55386.19,
    "volume": 199364
  },
  {
    "date": "2025-03-20",
    "open": 55386.19,
    "high": 56272.23,
    "low": 55107.04,
    "close": 55828.57,
    "volume": 175985
  },
  {
    "date": "2025-04-01",
    "open": 55828.57,
    "high": 56601.15,
    "low": 55781.09,
    "close": 56453.92,
    "volume": 313061
  },
  {
    "date": "2025-04-02",
    "open": 56453.92,
    "high": 56831.11,
    "low": 55420.12,
    "close": 55721.02,
    "volume": 175283
  },
  {
    "date": "2025-04-03",
    "open": 55721.02,
    "high": 56270.14,
    "low": 55678.33,
    "close": 55762.56,
    "volume": 146065
  },
  {
    "date": "2025-04-04",
    "open": 55762.56,
    "high": 56710.79,
    "low": 55415.91,
    "close": 56547.38,
    "volume": 111130
  },
  {
    "date": "2025-04-05",
    "open": 56547.38,
    "high": 56812.51,
    "low": 55904.17,
    "close": 56189.12,
    "volume": 222503
  },
  {
    "date": "2025-04-06",
    "open": 56189.12,
    "high": 56525.82,
    "low": 55184.61,
    "close": 55186.15,
    "volume": 168494
  },
  {
    "date": "2025-04-07",
    "open": 55186.15,
    "high": 56310.47,
    "low": 54834.8,
    "close": 56098.47,
    "volume": 123249
  },
  {
    "date": "2025-04-08",
    "open": 56098.47,
    "high": 56387.88,
    "low": 55553.3,
    "close": 55849.32,
    "volume": 206216
  },
  {
    "date": "2025-04-09",
    "open": 55849.32,
    "high": 55917.98,
    "low": 55407.82,
    "close": 55637.59,
    "volume": 309112
  },
  {
    "date": "2025-04-10",
    "open": 55637.59,
    "high": 55764.36,
    "low": 55008.11,
    "close": 55185.61,
    "volume": 273362
  },
  {
    "date": "2025-04-11",
    "open": 55185.61,
    "high": 55356.75,
    "low": 54158.41,
    "close": 54250.76,
    "volume": 251211
  },
  {
    "date": "2025-04-12",
    "open": 54250.76,
    "high": 54273.48,
    "low": 53653.89,
    "close": 54039.89,
    "volume": 263844
  },
  {
    "date": "2025-04-13",
    "open": 54039.89,
    "high": 54259.69,
    "low": 53904.09,
    "close": 54033.99,
    "volume": 257837
  },
  {
    "date": "2025-04-14",
    "open": 54033.99,
    "high": 55169.2,
    "low": 53700.01,
    "close": 54862.92,
    "volume": 306182
  },
  {
    "date": "2025-04-15",
    "open": 54862.92,
    "high": 56450.43,
    "low": 54435.75,
    "close": 56017.77,
    "volume": 349850
  },
  {
    "date": "2025-04-16",
    "open": 56017.77,
    "high": 57589.78,
    "low": 55914.27,
    "close": 57062.16,
    "volume": 116912
  },
  {
    "date": "2025-04-17",
    "open": 57062.16,
    "high": 57519.79,
    "low": 55601.36,
    "close": 56122.26,
    "volume": 326820
  },
  {
    "date": "2025-04-18",
    "open": 56122.26,
    "high": 56590.82,
    "low": 55871.3,
    "close": 55940.82,
    "volume": 245697
  },
  {
    "date": "2025-04-19",
    "open": 55940.82,
    "high": 57351.94,
    "low": 55794.47,
    "close": 56931.49,
    "volume": 292226
  },
  {
    "date": "2025-04-20",
    "open": 56931.49,
    "high": 57419.37,
    "low": 56344.37,
    "close": 56444.53,
    "volume": 348629
  },
  {
    "date": "2025-05-01",
    "open": 56444.53,
    "high": 56944.1,
    "low": 56303.97,
    "close": 56447.11,
    "volume": 150818
  },
  {
    "date": "2025-05-02",
    "open": 56447.11,
    "high": 56878.28,
    "low": 55936.84,
    "close": 56233.93,
    "volume": 116820
  },
  {
    "date": "2025-05-03",
    "open": 56233.93,
    "high": 56370.15,
    "low": 55692.85,
    "close": 56070.2,
    "volume": 137093
  },
  {
    "date": "2025-05-04",
    "open": 56070.2,
    "high": 56923.14,
    "low": 55904.71,
    "close": 56572.91,
    "volume": 144792
  },
  {
    "date": "2025-05-05",
    "open": 56572.91,
    "high": 57050.02,
    "low": 56195.58,
    "close": 56684.3,
    "volume": 180608
  },
  {
    "date": "2025-05-06",
    "open": 56684.3,
    "high": 56774.2,
    "low": 56400.02,
    "close": 56537.24,
    "volume": 210047
  },
  {
    "date": "2025-05-07",
    "open": 56537.24,
    "high": 57254.09,
    "low": 56128.9,
    "close": 57179.46,
    "volume": 321522
  },
  {
    "date": "2025-05-08",
    "open": 57179.46,
    "high": 57429.7,
    "low": 57002.44,
    "close": 57307.13,
    "volume": 304025
  },
  {
    "date": "2025-05-09",
    "open": 57307.13,
    "high": 57571.87,
    "low": 56778.18,
    "close": 56801.34,
    "volume": 202284
  },
  {
    "date": "2025-05-10",
    "open": 56801.34,
    "high": 57359.25,
    "low": 56170.53,
    "close": 56390.38,
    "volume": 192976
  },
  {
    "date": "2025-05-11",
    "open": 56390.38,
    "high": 57673.44,
    "low": 56226.51,
    "close": 57458.74,
    "volume": 328974
  },
  {
    "date": "2025-05-12",
    "open": 57458.74,
    "high": 57690.46,
    "low": 56340.67,
    "close": 56470.03,
    "volume": 277144
  },
  {
    "date": "2025-05-13",
    "open": 56470.03,
    "high": 56776.93,
    "low": 56131.22,
    "close": 56236.35,
    "volume": 150245
  },
  {
    "date": "2025-05-14",
    "open": 56236.35,
    "high": 57853.74,
    "low": 56223.27,
    "close": 57331.2,
    "volume": 122179
  },
  {
    "date": "2025-05-15",
    "open": 57331.2,
    "high": 57507.63,
    "low": 56871.02,
    "close": 57325.08,
    "volume": 326252
  },
  {
    "date": "2025-05-16",
    "open": 57325.08,
    "high": 57655.11,
    "low": 56444.35,
    "close": 56907.99,
    "volume": 232439
  },
  {
    "date": "2025-05-17",
    "open": 56907.99,
    "high": 57931.19,
    "low": 56779.45,
    "close": 57918.16,
    "volume": 128564
  },
  {
    "date": "2025-05-18",
    "open": 57918.16,
    "high": 58240.24,
    "low": 57387.98,
    "close": 57676.93,
    "volume": 146780
  },
  {
    "date": "2025-05-19",
    "open": 57676.93,
    "high": 58663.8,
    "low": 57258.48,
    "close": 58502.66,
    "volume": 135193
  },
  {
    "date": "2025-05-20",
    "open": 58502.66,
    "high": 58989.26,
    "low": 58450.72,
    "close": 58486.71,
    "volume": 280422
  },
  {
    "date": "2025-06-01",
    "open": 58486.71,
    "high": 58656.14,
    "low": 57804.77,
    "close": 58176.57,
    "volume": 323599
  },
  {
    "date": "2025-06-02",
    "open": 58176.57,
    "high": 58295.62,
    "low": 57630.25,
    "close": 57755.08,
    "volume": 300552
  },
  {
    "date": "2025-06-03",
    "open": 57755.08,
    "high": 58680.78,
    "low": 57451.16,
    "close": 58566.97,
    "volume": 253910
  },
  {
    "date": "2025-06-04",
    "open": 58566.97,
    "high": 58982.14,
    "low": 57968.45,
    "close": 58198.17,
    "volume": 158164
  },
  {
    "date": "2025-06-05",
    "open": 58198.17,
    "high": 59451.49,
    "low": 58145.76,
    "close": 58976.18,
    "volume": 286464
  },
  {
    "date": "2025-06-06",
    "open": 58976.18,
    "high": 59588.53,
    "low": 58550.81,
    "close": 59276.61,
    "volume": 306405
  },
  {
    "date": "2025-06-07",
    "open": 59276.61,
    "high": 59305.26,
    "low": 57879.54,
    "close": 58449.77,
    "volume": 163201
  },
  {
    "date": "2025-06-08",
    "open": 58449.77,
    "high": 59102.77,
    "low": 58334.05,
    "close": 58732.24,
    "volume": 156828
  },
  {
    "date": "2025-06-09",
    "open": 58732.24,
    "high": 59110.5,
    "low": 57359.61,
    "close": 57938.67,
    "volume": 110278
  },
  {
    "date": "2025-06-10",
    "open": 57938.67,
    "high": 59391.98,
    "low": 57519.56,
    "close": 58888.59,
    "volume": 121984
  },
  {
    "date": "2025-06-11",
    "open": 58888.59,
    "high": 60305.04,
    "low": 58591.27,
    "close": 59938.29,
    "volume": 298809
  },
  {
    "date": "2025-06-12",
    "open": 59938.29,
    "high": 61717.04,
    "low": 59881.17,
    "close": 61111.17,
    "volume": 231251
  },
  {
    "date": "2025-06-13",
    "open": 61111.17,
    "high": 62537.78,
    "low": 60670.99,
    "close": 62054.43,
    "volume": 237487
  },
  {
    "date": "2025-06-14",
    "open": 62054.43,
    "high": 63102.0,
    "low": 61939.73,
    "close": 63095.27,
    "volume": 315049
  },
  {
    "date": "2025-06-15",
    "open": 63095.27,
    "high": 63606.77,
    "low": 61606.62,
    "close": 61969.82,
    "volume": 187710
  },
  {
    "date": "2025-06-16",
    "open": 61969.82,
    "high": 62798.93,
    "low": 61890.56,
    "close": 62728.66,
    "volume": 256551
  },
  {
    "date": "2025-06-17",
    "open": 62728.66,
    "high": 62865.8,
    "low": 62296.84,
    "close": 62857.55,
    "volume": 187517
  },
  {
    "date": "2025-06-18",
    "open": 62857.55,
    "high": 63299.34,
    "low": 62691.11,
    "close": 62856.98,
    "volume": 174356
  },
  {
    "date": "2025-06-19",
    "open": 62856.98,
    "high": 64118.27,
    "low": 62253.33,
    "close": 63738.34,
    "volume": 338010
  },
  {
    "date": "2025-06-20",
    "open": 63738.34,
    "high": 63740.3,
    "low": 63198.1,
    "close": 63593.05,
    "volume": 156020
  }
]